{
  "description": "Nystatin-like Pseudonocardia polyene",
  "genbankAccession": "EU108007.1",
  "mibigAccession": "BGC0000116.1",
  "architecture": {
    "cppA": {
      "0": {
        "iterations": 1,
        "domains": {
          "AT": {
            "substrate": "mal"
          }
        }
      }
    },
    "cppB": {
      "0": {
        "iterations": 1,
        "domains": {
          "AT": {
            "substrate": "mmal"
          },
          "KR": {
            "type": "A2",
            "active": true
          }
        }
      },
      "1": {
        "iterations": 1,
        "domains": {
          "AT": {
            "substrate": "mmal"
          },
          "KR": {
            "type": "A1",
            "active": true
          }
        }
      }
    },
    "cppC": {
      "0": {
        "iterations": 1,
        "domains": {
          "AT": {
            "substrate": "mal"
          },
          "DH": {
            "active": true
          },
          "KR": {
            "type": "B1",
            "active": true
          }
        }
      },
      "1": {
        "iterations": 1,
        "domains": {
          "AT": {
            "substrate": "mal"
          },
          "DH": {
            "active": true
          },
          "KR": {
            "type": "B1",
            "active": true
          }
        }
      },
      "2": {
        "iterations": 1,
        "domains": {
          "AT": {
            "substrate": "mal"
          },
          "DH": {
            "active": true
          },
          "ER": {
            "active": true
          },
          "KR": {
            "type": "B1",
            "active": true
          }
        }
      },
      "3": {
        "iterations": 1,
        "domains": {
          "AT": {
            "substrate": "mal"
          },
          "DH": {
            "active": true
          },
          "KR": {
            "type": "B1",
            "active": true
          }
        }
      },
      "4": {
        "iterations": 1,
        "domains": {
          "AT": {
            "substrate": "mal"
          },
          "DH": {
            "active": true
          },
          "KR": {
            "type": "B1",
            "active": true
          }
        }
      },
      "5": {
        "iterations": 1,
        "domains": {
          "AT": {
            "substrate": "mal"
          },
          "DH": {
            "active": true
          },
          "KR": {
            "type": "B1",
            "active": true
          }
        }
      }
    },
    "cppI": {
      "0": {
        "iterations": 1,
        "domains": {
          "AT": {
            "substrate": "mal"
          },
          "DH": {
            "active": true
          },
          "KR": {
            "type": "B1",
            "active": true
          }
        }
      },
      "1": {
        "iterations": 1,
        "domains": {
          "AT": {
            "substrate": "mal"
          },
          "KR": {
            "type": "A1",
            "active": true
          }
        }
      },
      "2": {
        "iterations": 1,
        "domains": {
          "AT": {
            "substrate": "mmal"
          },
          "KR": {
            "type": "A2",
            "active": true
          }
        }
      },
      "3": {
        "iterations": 1,
        "domains": {
          "AT": {
            "substrate": "mal"
          },
          "KR": {
            "type": "B1",
            "active": true
          }
        }
      },
      "4": {
        "iterations": 1,
        "domains": {
          "AT": {
            "substrate": "mal"
          },
          "KR": {
            "type": "C1",
            "active": true
          }
        }
      },
      "5": {
        "iterations": 1,
        "domains": {
          "AT": {
            "substrate": "mal"
          },
          "KR": {
            "type": "B1",
            "active": true
          }
        }
      }
    },
    "cppJ": {
      "0": {
        "iterations": 1,
        "domains": {
          "AT": {
            "substrate": "mal"
          },
          "DH": {
            "active": true
          },
          "ER": {
            "active": true
          },
          "KR": {
            "type": "B1",
            "active": true
          }
        }
      },
      "1": {
        "iterations": 1,
        "domains": {
          "AT": {
            "substrate": "mal"
          },
          "KR": {
            "type": "B1",
            "active": true
          }
        }
      },
      "2": {
        "iterations": 1,
        "domains": {
          "AT": {
            "substrate": "mal"
          },
          "DH": {
            "active": false
          },
          "KR": {
            "type": "B1",
            "active": true
          }
        }
      }
    },
    "cppK": {
      "0": {
        "iterations": 1,
        "domains": {
          "AT": {
            "substrate": "mal"
          },
          "DH": {
            "active": false
          },
          "KR": {
            "type": "B1",
            "active": true
          },
          "TE": {
            "ring": 0,
            "cyclic": true
          }
        }
      }
    }
  }
}